comotore/__init__.py
comotore/base/__init__.py
comotore/base/assembly.py
comotore/base/component.py
comotore/base/engine.py
comotore/base/external.py
comotore/errors/__init__.py
comotore/errors/error_end_of_response.py
comotore/errors/error_timeout_response.py
comotore/helpers/__init__.py
comotore/helpers/runner.py
comotore/locations/__init__.py
comotore/locations/process_location.py
comotore/logging/__init__.py
comotore/logging/formatters/__init__.py
comotore/logging/formatters/plain_formatter.py
comotore/logging/handlers/__init__.py
comotore/logging/handlers/callback_dict_handler.py
comotore/logging/handlers/callback_record_handler.py
comotore/logging/loggers/__init__.py
comotore/logging/loggers/comotore_logger.py
comotore-19.12.2.dist-info/LICENSE
comotore-19.12.2.dist-info/METADATA
comotore-19.12.2.dist-info/WHEEL
comotore-19.12.2.dist-info/top_level.txt
comotore-19.12.2.dist-info/RECORD
