Metadata-Version: 2.1
Name: comotore
Version: 19.12.2
Summary: comotore - component engine library - simple actor model realisation
Home-page: UNKNOWN
Author: Zaglyadskiy Alexander
Author-email: rlllx33@gmail.com
License: The MIT License
Platform: UNKNOWN
Classifier: Development Status :: 3 - Alpha
Classifier: Framework :: AsyncIO
Classifier: Intended Audience :: Developers
Classifier: License :: OSI Approved :: MIT License
Classifier: Operating System :: MacOS
Classifier: Operating System :: Microsoft :: Windows
Classifier: Operating System :: POSIX :: Linux
Classifier: Programming Language :: Python :: 3
Classifier: Programming Language :: Python :: 3.7
Classifier: Topic :: Software Development
Classifier: Topic :: Software Development :: Libraries
Requires-Dist: async-timeout (<4,>=3.0.1)
